sphcpy/__init__.py
sphcpy/constants.py
sphcpy/dataslice.py
sphcpy/utilities.py
sphcpy-0.0.5.data/scripts/p2VTK
sphcpy-0.0.5.dist-info/DESCRIPTION.rst
sphcpy-0.0.5.dist-info/METADATA
sphcpy-0.0.5.dist-info/RECORD
sphcpy-0.0.5.dist-info/WHEEL
sphcpy-0.0.5.dist-info/metadata.json
sphcpy-0.0.5.dist-info/top_level.txt
