Metadata-Version: 2.0
Name: sphcpy
Version: 0.0.5
Summary: Wrappers and tools for reading and plotting p.XX data from SPHC
Home-page: https://github.com/viper2642/sphcpy
Author: David Pfefferle
Author-email: david.pfefferle@uwa.edu.au
License: GPL-3.0
Keywords: plot SPH VTK
Platform: UNKNOWN
Classifier: Development Status :: 3 - Alpha
Classifier: Programming Language :: Python :: 2.7
Classifier: Topic :: Scientific/Engineering :: Visualization
Requires-Dist: numpy
Requires-Dist: pyevtk
